localtts/__init__.py
localtts/kokoro_wrapper.py
localtts-20250621.1.dist-info/licenses/LICENSE
localtts-20250621.1.dist-info/METADATA
localtts-20250621.1.dist-info/WHEEL
localtts-20250621.1.dist-info/top_level.txt
localtts-20250621.1.dist-info/RECORD
