Metadata-Version: 2.4
Name: localTTS
Version: 20250621.1
Summary: Your local TTS model inference framework.
License: MIT license
Requires-Python: >=3.8
License-File: LICENSE
Provides-Extra: kokoro
Requires-Dist: kokoro; extra == "kokoro"
Dynamic: license-file
